Workbook

Sheet Visão
B8: CONFIGURAÇÕES
B9: Salário | D9: 5600
B10: Rendimento Carteira | D10: 0.01
B11: Sugestão de Investimento (30%) | D11: =D9*30% -> 1680
B13: PERFIL | D13: Conservador
B14: VALOR DO INVESTIMENTO MENSAL | D14: =D11 -> 1680
B16: TIPO DE FII | C16: % Sugerido | D16: Valores
B17: Papel | C17: =VLOOKUP($D$13&"-"&B17,BaseApoio!$B:$E,4,0) -> 0.3 | D17: =C17*$D$14 -> 504
B18: Tijolo | C18: =VLOOKUP($D$13&"-"&B18,BaseApoio!$B:$E,4,0) -> 0.5 | D18: =C18*$D$14 -> 840
B19: Híbrido | C19: =VLOOKUP($D$13&"-"&B19,BaseApoio!$B:$E,4,0) -> 0.05 | D19: =C19*$D$14 -> 84
B20: FOFs | C20: =VLOOKUP($D$13&"-"&B20,BaseApoio!$B:$E,4,0) -> 0.05 | D20: =C20*$D$14 -> 84
B21: Desenvolvimento | C21: =VLOOKUP($D$13&"-"&B21,BaseApoio!$B:$E,4,0) -> 0 | D21: =C21*$D$14 -> 0
B22: Hotelaria | C22: =VLOOKUP($D$13&"-"&B22,BaseApoio!$B:$E,4,0) -> 0.1 | D22: =C22*$D$14 -> 168
D23: =SUM(D17:D22) -> 1680
B25: INVESTIMENTO MENSAL
B26: Quanto investir por mês ? | D26: 1200
B27: Por Quantos Anos ? | D27: 5
B28: Taxa de Rendimento mensal ? | D28: 0.01079
B29: Patrimônio acumulado ? | D29: =FV(D28,D27*12,D26*-1) -> 100532.3
B30: Dividendos Mensais ? | D30: =D29*D10 -> 1005.323
A31: 2
A32: 5 | B32: Cenários | D32: Dividendo
A33: 10 | B33: Projeção para 2 Anos ? | C33: =FV($D$28,$A31*12,$D$26*-1) -> 32673.153 | D33: =C33*$D$10 -> 326.73153
A34: 20 | B34: Projeção para 5 Anos ? | C34: =FV($D$28,$A32*12,$D$26*-1) -> 100532.3 | D34: =C34*$D$10 -> 1005.323
A35: 30 | B35: Projeção para 10 Anos ? | C35: =FV($D$28,$A33*12,$D$26*-1) -> 291941.06 | D35: =C35*$D$10 -> 2919.4106
B36: Projeção para 20 Anos ? | C36: =FV($D$28,$A34*12,$D$26*-1) -> 1350238.1 | D36: =C36*$D$10 -> 13502.381
B37: Projeção para 30 Anos ? | C37: =FV($D$28,$A35*12,$D$26*-1) -> 5186603.6 | D37: =C37*$D$10 -> 51866.036

Sheet BaseApoio
B2: CHAVE | C2: PERFIL | D2: TIPO DE FII | E2: % | H2: PERFIL
B3: =C3&"-"&D3 -> Conservador-Papel | C3: Conservador | D3: Papel | E3: 0.3 | H3: Agressivo
B4: =C4&"-"&D4 -> Conservador-Tijolo | C4: Conservador | D4: Tijolo | E4: 0.5 | H4: Conservador
B5: =C5&"-"&D5 -> Conservador-Híbrido | C5: Conservador | D5: Híbrido | E5: 0.05 | H5: Moderado
B6: =C6&"-"&D6 -> Conservador-FOFs | C6: Conservador | D6: FOFs | E6: 0.05
B7: =C7&"-"&D7 -> Conservador-Desenvolvimento | C7: Conservador | D7: Desenvolvimento | E7: 0
B8: =C8&"-"&D8 -> Conservador-Hotelaria | C8: Conservador | D8: Hotelaria | E8: 0.1 | F8: =SUM(E3:E8) -> 1
B9: =C9&"-"&D9 -> Moderado-Papel | C9: Moderado | D9: Papel | E9: 0.25
B10: =C10&"-"&D10 -> Moderado-Tijolo | C10: Moderado | D10: Tijolo | E10: 0.35
B11: =C11&"-"&D11 -> Moderado-Híbrido | C11: Moderado | D11: Híbrido | E11: 0.1
B12: =C12&"-"&D12 -> Moderado-FOFs | C12: Moderado | D12: FOFs | E12: 0.05
B13: =C13&"-"&D13 -> Moderado-Desenvolvimento | C13: Moderado | D13: Desenvolvimento | E13: 0.1
B14: =C14&"-"&D14 -> Moderado-Hotelaria | C14: Moderado | D14: Hotelaria | E14: 0.15 | F14: =SUM(E9:E14) -> 1
B15: =C15&"-"&D15 -> Agressivo-Papel | C15: Agressivo | D15: Papel | E15: 0.25
B16: =C16&"-"&D16 -> Agressivo-Tijolo | C16: Agressivo | D16: Tijolo | E16: 0.15
B17: =C17&"-"&D17 -> Agressivo-Híbrido | C17: Agressivo | D17: Híbrido | E17: 0.15
B18: =C18&"-"&D18 -> Agressivo-FOFs | C18: Agressivo | D18: FOFs | E18: 0.1
B19: =C19&"-"&D19 -> Agressivo-Desenvolvimento | C19: Agressivo | D19: Desenvolvimento | E19: 0.25
B20: =C20&"-"&D20 -> Agressivo-Hotelaria | C20: Agressivo | D20: Hotelaria | E20: 0.1 | F20: =SUM(E15:E20) -> 1
